get_gcp_secret/__init__.py
get_gcp_secret-0.0.5.dist-info/LICENSE
get_gcp_secret-0.0.5.dist-info/METADATA
get_gcp_secret-0.0.5.dist-info/WHEEL
get_gcp_secret-0.0.5.dist-info/top_level.txt
get_gcp_secret-0.0.5.dist-info/RECORD
