Metadata-Version: 2.1
Name: get-gcp-secret
Version: 0.0.5
Summary: Get value from Google Cloud Secret Manager.
Home-page: https://github.com/hisashimurai/get_gcp_secret
Author: Hisashi Murai
Author-email: xyksp956@yahoo.co.jp
License: MIT
Keywords: GAE GCF GCP secret-manager
Platform: UNKNOWN
Classifier: Programming Language :: Python :: 3
Classifier: Programming Language :: Python :: 3.7
Classifier: Programming Language :: Python :: 3.8
Classifier: Programming Language :: Python :: 3.9
Classifier: License :: OSI Approved :: MIT License
Requires-Python: >=3.7
Requires-Dist: google-cloud-secret-manager
